odoo/addons/repair_timeline/README.rst
odoo/addons/repair_timeline/__init__.py
odoo/addons/repair_timeline/__manifest__.py
odoo/addons/repair_timeline/i18n/pt_BR.po
odoo/addons/repair_timeline/i18n/repair_timeline.pot
odoo/addons/repair_timeline/readme/CONTRIBUTORS.rst
odoo/addons/repair_timeline/readme/CREDITS.rst
odoo/addons/repair_timeline/readme/DESCRIPTION.rst
odoo/addons/repair_timeline/static/description/banner.png
odoo/addons/repair_timeline/static/description/icon.png
odoo/addons/repair_timeline/static/description/index.html
odoo/addons/repair_timeline/views/repair_order.xml
odoo12_addon_repair_timeline-12.0.1.0.2.dist-info/METADATA
odoo12_addon_repair_timeline-12.0.1.0.2.dist-info/WHEEL
odoo12_addon_repair_timeline-12.0.1.0.2.dist-info/top_level.txt
odoo12_addon_repair_timeline-12.0.1.0.2.dist-info/RECORD
